ezcalour_module/__init__.py
ezcalour_module/ezcalour.config
ezcalour_module/ezcalour.config.bak
ezcalour_module/ezcalour.py
ezcalour_module/hook-calour.py
ezcalour_module/hook-skbio.py
ezcalour_module/log.cfg
ezcalour_module/util.py
ezcalour_module/ui/CalourGUI.ui
ezcalour_module/ui/CalourGUILoad.ui
ezcalour_module/ui/list_select.ui
ezcalour-1.12.4.dist-info/METADATA
ezcalour-1.12.4.dist-info/WHEEL
ezcalour-1.12.4.dist-info/entry_points.txt
ezcalour-1.12.4.dist-info/top_level.txt
ezcalour-1.12.4.dist-info/RECORD
