Metadata-Version: 2.1
Name: ezcalour
Version: 1.12.4
Summary: EZCalour: GUI frontend tool for Calour microbiome analysis software
Home-page: http://microbio.me/calour
Author: calour development team
Maintainer: calour development team
License: GPL
Keywords: microbiome heatmap analysis bioinformatics GUI
Platform: UNKNOWN
Classifier: Development Status :: 2 - Pre-Alpha
Classifier: License :: OSI Approved :: BSD License
Classifier: Environment :: Console
Classifier: Topic :: Software Development :: Libraries :: Application Frameworks
Classifier: Topic :: Scientific/Engineering
Classifier: Topic :: Scientific/Engineering :: Bio-Informatics
Classifier: Programming Language :: Python
Classifier: Programming Language :: Python :: 3
Classifier: Programming Language :: Python :: 3.5
Classifier: Programming Language :: Python :: 3.6
Classifier: Operating System :: Unix
Classifier: Operating System :: POSIX
Classifier: Operating System :: MacOS :: MacOS X
Classifier: Operating System :: Microsoft :: Windows
Requires-Dist: matplotlib
Requires-Dist: pyqt5
Requires-Dist: numpy
Requires-Dist: calour
Requires-Dist: dbbact-calour
Provides-Extra: coverage
Requires-Dist: coverage ; extra == 'coverage'
Provides-Extra: doc
Requires-Dist: Sphinx (>=1.4) ; extra == 'doc'
Provides-Extra: test
Requires-Dist: nose ; extra == 'test'
Requires-Dist: pep8 ; extra == 'test'
Requires-Dist: flake8 ; extra == 'test'
